nn_drawer
