Metadata-Version: 2.1
Name: nn_drawer
Version: 0.0.4
Summary: Иструмент для визуализации структуры нейронных сетей.
Home-page: https://github.com/EvgeniBondarev/Neural-Network-Drawer.git
Download-URL: https://github.com/EvgeniBondarev/Neural-Network-Drawer/archive/refs/heads/master.zip
Author: nn_drawer
Author-email: peoplesdreamer@gmail.ru
License: Apache License, Version 2.0, see LICENSE file
Classifier: License :: OSI Approved :: Apache Software License
Classifier: Operating System :: OS Independent
Classifier: Intended Audience :: End Users/Desktop
Classifier: Intended Audience :: Developers
Classifier: Programming Language :: Python
Classifier: Programming Language :: Python :: 3.6
Classifier: Programming Language :: Python :: 3.7
Classifier: Programming Language :: Python :: 3.8
Classifier: Programming Language :: Python :: 3.10
Classifier: Programming Language :: Python :: 3.11
Classifier: Programming Language :: Python :: 3.12
Classifier: Programming Language :: Python :: Implementation :: PyPy
Classifier: Programming Language :: Python :: Implementation :: CPython
Requires-Dist: matplotlib
